elecmon/__init__.py
elecmon/config-template.yml
elecmon/elecmon.py
elecmon/data/energy_template.db
elecmon-0.0.6.dist-info/METADATA
elecmon-0.0.6.dist-info/WHEEL
elecmon-0.0.6.dist-info/top_level.txt
elecmon-0.0.6.dist-info/RECORD
