Metadata-Version: 2.1
Name: elecmon
Version: 0.0.6
Summary: Electricity monitor library
Home-page: https://github.com/Phornee/elecmon
Author: Ismael Raya
Author-email: phornee@gmail.com
License: UNKNOWN
Platform: UNKNOWN
Classifier: Programming Language :: Python :: 3
Classifier: License :: OSI Approved :: MIT License
Classifier: Operating System :: OS Independent
Classifier: Topic :: Home Automation
Requires-Python: >=3.6
Requires-Dist: baseutils-phornee (>=0.1.1)
